pyesi_client/__init__.py
pyesi_client/constants.py
pyesi_client/core/__init__.py
pyesi_client/core/auth.py
pyesi_client/core/client.py
pyesi_client/core/metadata_manager.py
pyesi_client/core/scope_manager.py
pyesi_client/models/__init__.py
pyesi_client/models/auth_models.py
pyesi_client/models/jwk_models.py
pyesi_client/models/token_models.py
pyesi_client-0.1.1.dist-info/METADATA
pyesi_client-0.1.1.dist-info/WHEEL
pyesi_client-0.1.1.dist-info/licenses/LICENSE
pyesi_client-0.1.1.dist-info/RECORD
