Metadata-Version: 2.4
Name: pyesi-client
Version: 0.1.1
Summary: EVE Online ESI client library built on pyesi-openapi with caching and utilities
Project-URL: Repository, https://github.com/arxbombus/pyesi-client
Author-email: arxbombus <arxbombus@gmail.com>
License: MIT License
License-File: LICENSE
Requires-Python: >=3.13
Requires-Dist: cryptography>=45.0.7
Requires-Dist: pydantic>=2.0.0
Requires-Dist: pyesi-openapi>=0.1.0
Requires-Dist: pyjwt>=2.10.1
